{
  "build_id": "1QMi",
  "url": "https://www.d2core.com/d4/planner?bd=1QMi",
  "success": true,
  "markdown": "搜索...\n\n语言登录\n\n暗黑4技能模拟器 \\| 暗黑核\n\n[![](https://cloudstorage.d2core.com/app/logo/logo.png?imageView2/2/ignore-error/1/w/84/q/80)\\\\\n\\\\\n![](https://cloudstorage.d2core.com/app/logo-fav-32-solid.png)](https://www.d2core.com/)偏好[暗黑破坏神4](https://www.d2core.com/d4)[社区](https://www.d2core.com/bbs?game=d4)[构筑](https://www.d2core.com/d4/builds)[模拟器](https://www.d2core.com/d4/planner)[数据库](https://www.d2core.com/d4/data)发现[暗黑破坏神2](https://www.d2core.com/d2r)[流放之路：降临](https://www.d2core.com/poe2)[火炬之光：无限](https://www.d2core.com/tli)[最后纪元](https://www.d2core.com/le)[发布内容](https://www.d2core.com/bbs/publish)[抖音@班登](https://www.douyin.com/user/MS4wLjABAAAAa1tL9sCX2--L33XhPMqXYcc0imsb5GJDYG-vZgUXq22JCkGBEgFSn7--z0RE_Wwq) [Bilibili@班登](https://space.bilibili.com/906997)暗黑核小程序\n\n![](https://cloudstorage.d2core.com/app/qrcode-light-new.jpg?imageView2/format/webp/q/80)\n\n![](https://www.d2core.com/static/tabbar/tab-home-fill.png)\n\n首页\n\n![](https://www.d2core.com/static/tabbar/tab-builds.png)\n\n构筑\n\n![](https://www.d2core.com/static/tabbar/tab-my.png)\n\n我的\n\nBD未公开\n\n加载中...\n\n验证码\n\n安全验证\n\n返回\n\n拖动下方滑块完成拼图\n\n确定\n\n![](<Base64-Image-Removed>)![](<Base64-Image-Removed>)\n\n![](<Base64-Image-Removed>)![](<Base64-Image-Removed>)\n\n![](<Base64-Image-Removed>)![](<Base64-Image-Removed>)\n\n![](<Base64-Image-Removed>)![](<Base64-Image-Removed>)\n\n![](<Base64-Image-Removed>)\n\nAI生成背景\n\n![success](<Base64-Image-Removed>)\n\n![](<Base64-Image-Removed>)\n\n我不会\n\n![](<Base64-Image-Removed>)\n\n常规验证\n\n![feedback](<Base64-Image-Removed>)\n\n![refresh](<Base64-Image-Removed>)\n\n![close](<Base64-Image-Removed>)\n\n确定",
  "text": ""
}